odoo/addons/test_base_binary_url_import/README.rst
odoo/addons/test_base_binary_url_import/__init__.py
odoo/addons/test_base_binary_url_import/__manifest__.py
odoo/addons/test_base_binary_url_import/demo/demo_test_binary.xml
odoo/addons/test_base_binary_url_import/demo/ir_attachment.xml
odoo/addons/test_base_binary_url_import/i18n/es.po
odoo/addons/test_base_binary_url_import/i18n/it.po
odoo/addons/test_base_binary_url_import/i18n/test_base_binary_url_import.pot
odoo/addons/test_base_binary_url_import/models/__init__.py
odoo/addons/test_base_binary_url_import/models/test_binary.py
odoo/addons/test_base_binary_url_import/readme/CONTRIBUTORS.rst
odoo/addons/test_base_binary_url_import/readme/CREDITS.rst
odoo/addons/test_base_binary_url_import/readme/DESCRIPTION.rst
odoo/addons/test_base_binary_url_import/security/ir.model.access.csv
odoo/addons/test_base_binary_url_import/static/description/icon.png
odoo/addons/test_base_binary_url_import/static/description/index.html
odoo/addons/test_base_binary_url_import/tests/__init__.py
odoo/addons/test_base_binary_url_import/tests/test_binary_import.py
odoo/addons/test_base_binary_url_import/tests/test_ir_attachment_import.py
odoo/addons/test_base_binary_url_import/tests/files/test.pdf
odoo/addons/test_base_binary_url_import/tests/files/test.txt
odoo/addons/test_base_binary_url_import/views/test_binary.xml
odoo_addon_test_base_binary_url_import-16.0.1.0.1.2.dist-info/METADATA
odoo_addon_test_base_binary_url_import-16.0.1.0.1.2.dist-info/WHEEL
odoo_addon_test_base_binary_url_import-16.0.1.0.1.2.dist-info/top_level.txt
odoo_addon_test_base_binary_url_import-16.0.1.0.1.2.dist-info/RECORD
